{
  "match_id": "1-a2ac26de-9f00-45d8-af78-30b7f3679c50",
  "version": 2,
  "game": "csgo",
  "region": "EU",
  "competition_id": "e056975c-09ff-4290-8fcd-596cd7295152",
  "competition_type": "championship",
  "competition_name": "ESEA S46 EU Open Central",
  "organizer_id": "08b06cfc-74d0-454b-9a51-feda4b6b18da",
  "teams": {
    "faction2": {
      "faction_id": "8e384ed5-b50a-4b22-bbab-7b0f2a747c47",
      "leader": "eaf64179-f846-4ce0-b367-a3c0bec6376c",
      "avatar": "https://distribution.faceit-cdn.net/images/1aeea232-5b29-4eef-baa0-4b20c5b1ab9c.jpeg",
      "roster": [
        {
          "player_id": "eaf64179-f846-4ce0-b367-a3c0bec6376c",
          "nickname": "Kaabik",
          "avatar": "https://assets.faceit-cdn.net/avatars/eaf64179-f846-4ce0-b367-a3c0bec6376c_1550581404157.jpg",
          "membership": "esea",
          "game_player_id": "76561198076646996",
          "game_player_name": "Kääbik",
          "game_skill_level": 10,
          "anticheat_required": true
        },
        {
          "player_id": "91bc87c1-58cd-4c9d-803e-459f07aae917",
          "nickname": "Iiro",
          "avatar": "https://assets.faceit-cdn.net/avatars/91bc87c1-58cd-4c9d-803e-459f07aae917_1616435770623.jpg",
          "membership": "esea",
          "game_player_id": "76561198147461612",
          "game_player_name": "Iiro",
          "game_skill_level": 9,
          "anticheat_required": true
        },
        {
          "player_id": "c7087fd6-5c82-4c24-b740-93a6353077b3",
          "nickname": "Cimmo",
          "avatar": "https://distribution.faceit-cdn.net/images/4bd0e983-b914-462c-ae3b-011d1d892006.jpeg",
          "membership": "premium",
          "game_player_id": "76561198163502115",
          "game_player_name": "Retar",
          "game_skill_level": 10,
          "anticheat_required": true
        },
        {
          "player_id": "1e807c3f-f695-4519-87e7-266aa6d2e2de",
          "nickname": "karppaN",
          "avatar": "https://distribution.faceit-cdn.net/images/51c9dfca-21ac-4b9e-8b5f-9edd53ed1d6a.jpeg",
          "membership": "esea",
          "game_player_id": "76561198150546232",
          "game_player_name": "karppaN",
          "game_skill_level": 10,
          "anticheat_required": true
        },
        {
          "player_id": "107e531a-c25f-4ae1-8700-b682fe66579c",
          "nickname": "Senzej",
          "avatar": "https://assets.faceit-cdn.net/avatars/107e531a-c25f-4ae1-8700-b682fe66579c_1550497622001.jpg",
          "membership": "esea",
          "game_player_id": "76561198131723663",
          "game_player_name": "SenZeJ",
          "game_skill_level": 10,
          "anticheat_required": true
        },
        {
          "player_id": "13ec4253-e628-45b0-97cf-cc82bec02907",
          "nickname": "Sepmohn",
          "avatar": "https://distribution.faceit-cdn.net/images/66a45bc2-5200-4253-b379-0572b3bfb01f.jpeg",
          "membership": "esea",
          "game_player_id": "76561198434443199",
          "game_player_name": "Sep",
          "game_skill_level": 10,
          "anticheat_required": true
        }
      ],
      "substituted": false,
      "name": "Luura",
      "type": "premade"
    },
    "faction1": {
      "faction_id": "9e913b79-e204-4285-90cb-6a9fbdca32f3",
      "leader": "7dd555af-b3c8-4838-9b9c-0bfe73d16c68",
      "avatar": "https://distribution.faceit-cdn.net/images/505edb04-5202-46d7-8276-e43ed4c3b8ed.jpeg",
      "roster": [
        {
          "player_id": "7dd555af-b3c8-4838-9b9c-0bfe73d16c68",
          "nickname": "swanic",
          "avatar": "https://distribution.faceit-cdn.net/images/505edb04-5202-46d7-8276-e43ed4c3b8ed.jpeg",
          "membership": "premium",
          "game_player_id": "76561198117053817",
          "game_player_name": "swanic ツ",
          "game_skill_level": 10,
          "anticheat_required": true
        },
        {
          "player_id": "61baa843-926e-4df8-b24d-114876a717c6",
          "nickname": "NivramTTV",
          "avatar": "https://distribution.faceit-cdn.net/images/395f1302-9abf-4286-a19c-ef6ac5aed5d5.jpeg",
          "membership": "esea",
          "game_player_id": "76561198218305047",
          "game_player_name": "NivramTTV",
          "game_skill_level": 10,
          "anticheat_required": true
        },
        {
          "player_id": "8b6b0878-d182-4183-ba47-def3fa52a3be",
          "nickname": "Libra2k",
          "avatar": "https://distribution.faceit-cdn.net/images/b01cfcdf-a417-432c-88ee-d6b979b88cd2.jpeg",
          "membership": "premium",
          "game_player_id": "76561198983606682",
          "game_player_name": "Libra2k",
          "game_skill_level": 10,
          "anticheat_required": true
        },
        {
          "player_id": "9a3bf080-a281-4e45-b1c8-2a90c7423d25",
          "nickname": "-JJ-",
          "avatar": "https://distribution.faceit-cdn.net/images/49302532-8e0b-4337-978c-4dfbdfe7abc2.jpeg",
          "membership": "esea",
          "game_player_id": "76561198363680426",
          "game_player_name": "JJ",
          "game_skill_level": 10,
          "anticheat_required": true
        },
        {
          "player_id": "301d0c16-0c2e-4157-8ae5-78741205a99e",
          "nickname": "Tgg",
          "avatar": "https://distribution.faceit-cdn.net/images/271060c1-680f-4ea8-832c-5b9d5f841a63.jpeg",
          "membership": "esea",
          "game_player_id": "76561198407806571",
          "game_player_name": "Tg",
          "game_skill_level": 10,
          "anticheat_required": true
        },
        {
          "player_id": "b9bb3600-ab9b-4740-8bf8-c63cc38abc33",
          "nickname": "HokieDokie",
          "avatar": "https://distribution.faceit-cdn.net/images/11d7cdc8-bcfe-4181-b65d-5876500b4a13.jpeg",
          "membership": "premium",
          "game_player_id": "76561198003667658",
          "game_player_name": "HokieDokiee",
          "game_skill_level": 10,
          "anticheat_required": true
        },
        {
          "player_id": "ed88ed5f-c7eb-46b4-976b-3835e6d87c14",
          "nickname": "kianC",
          "avatar": "https://distribution.faceit-cdn.net/images/429d454b-0599-4819-ae25-6c137f71032d.jpeg",
          "membership": "esea",
          "game_player_id": "76561198157735200",
          "game_player_name": "kian",
          "game_skill_level": 10,
          "anticheat_required": true
        }
      ],
      "substituted": false,
      "name": "Poundland",
      "type": "premade"
    }
  },
  "voting": {
    "voted_entity_types": [
      "location",
      "map"
    ],
    "location": {
      "entities": [
        {
          "name": "Germany",
          "class_name": "Germany",
          "game_location_id": "Germany",
          "guid": "Germany",
          "image_lg": "https://cdn.faceit.com/games/votables/countries/de_428x212.jpg",
          "image_sm": "https://cdn.faceit.com/games/votables/countries/de_110x55.jpg"
        },
        {
          "image_lg": "https://cdn.faceit.com/games/votables/countries/fr_428x212.jpg",
          "image_sm": "https://cdn.faceit.com/games/votables/countries/fr_110x55.jpg",
          "name": "France",
          "class_name": "France",
          "game_location_id": "France",
          "guid": "France"
        },
        {
          "class_name": "Sweden",
          "game_location_id": "Sweden",
          "guid": "Sweden",
          "image_lg": "https://cdn.faceit.com/games/votables/countries/se_428x212.jpg",
          "image_sm": "https://cdn.faceit.com/games/votables/countries/se_110x55.jpg",
          "name": "Sweden"
        },
        {
          "image_sm": "https://cdn.faceit.com/games/votables/countries/uk_110x55.jpg",
          "name": "UK",
          "class_name": "UK",
          "game_location_id": "UK",
          "guid": "UK",
          "image_lg": "https://cdn.faceit.com/games/votables/countries/uk_428x212.jpg"
        },
        {
          "class_name": "Netherlands",
          "game_location_id": "Netherlands",
          "guid": "Netherlands",
          "image_lg": "https://cdn.faceit.com/games/votables/countries/nl_428x212.jpg",
          "image_sm": "https://cdn.faceit.com/games/votables/countries/nl_110x55.jpg",
          "name": "Netherlands"
        },
        {
          "guid": "ESEA-Warsaw",
          "image_lg": "https://cdn.faceit.com/games/votables/countries/pl_428x212.jpg",
          "image_sm": "https://cdn.faceit.com/games/votables/countries/pl_110x55.jpg",
          "name": "ESEA-Warsaw",
          "class_name": "ESEA-Warsaw",
          "game_location_id": "ESEA-Warsaw"
        },
        {
          "guid": "ESEA-Istanbul",
          "image_lg": "https://cdn.faceit.com/games/votables/countries/tr_428x212.jpg",
          "image_sm": "https://cdn.faceit.com/games/votables/countries/tr_110x55.jpg",
          "name": "ESEA-Istanbul",
          "class_name": "ESEA-Istanbul",
          "game_location_id": "ESEA-Istanbul"
        },
        {
          "image_sm": "https://cdn.faceit.com/games/votables/countries/es_110x55.jpg",
          "name": "ESEA-Madrid",
          "class_name": "ESEA-Madrid",
          "game_location_id": "ESEA-Madrid",
          "guid": "ESEA-Madrid",
          "image_lg": "https://cdn.faceit.com/games/votables/countries/es_428x212.jpg"
        }
      ],
      "pick": [
        "UK"
      ]
    },
    "map": {
      "entities": [
        {
          "name": "Inferno",
          "class_name": "de_inferno",
          "game_map_id": "de_inferno",
          "guid": "de_inferno",
          "image_lg": "https://assets.faceit-cdn.net/third_party/games/4f899245-2fa8-4e52-ad9a-4a363613c19e/assets/votables/696875d8-f504-44ff-9f4f-26bd81a237fe_1589575508999.jpeg",
          "image_sm": "https://assets.faceit-cdn.net/third_party/games/4f899245-2fa8-4e52-ad9a-4a363613c19e/assets/votables/007bc454-3d90-4e47-8ba6-a567e07741f0_1589193843230.jpeg"
        },
        {
          "guid": "de_vertigo",
          "image_lg": "https://assets.faceit-cdn.net/third_party/games/4f899245-2fa8-4e52-ad9a-4a363613c19e/assets/votables/973a97e8-680b-4e78-ae80-f18b0cb22f17_1589578674213.jpeg",
          "image_sm": "https://assets.faceit-cdn.net/third_party/games/4f899245-2fa8-4e52-ad9a-4a363613c19e/assets/votables/0b16dd4c-fc45-4b39-8488-62d362545a4a_1594388355393.jpeg",
          "name": "Vertigo",
          "class_name": "de_vertigo",
          "game_map_id": "de_vertigo"
        },
        {
          "class_name": "de_ancient",
          "game_map_id": "de_ancient",
          "guid": "de_ancient",
          "image_lg": "https://assets.faceit-cdn.net/third_party/games/4f899245-2fa8-4e52-ad9a-4a363613c19e/assets/votables/61e9180e-eddc-4cd8-93e1-074a60788013_1607106287430.jpeg",
          "image_sm": "https://assets.faceit-cdn.net/third_party/games/4f899245-2fa8-4e52-ad9a-4a363613c19e/assets/votables/7e1736a3-8ea9-4e2b-9bfc-2b0c97105823_1607106278884.jpeg",
          "name": "Ancient"
        },
        {
          "name": "Mirage",
          "class_name": "de_mirage",
          "game_map_id": "de_mirage",
          "guid": "de_mirage",
          "image_lg": "https://assets.faceit-cdn.net/third_party/games/4f899245-2fa8-4e52-ad9a-4a363613c19e/assets/votables/b846f806-1957-4456-952e-e0f85233b5d7_1589195893467.jpeg",
          "image_sm": "https://assets.faceit-cdn.net/third_party/games/4f899245-2fa8-4e52-ad9a-4a363613c19e/assets/votables/30358226-693b-4b9d-9da9-afd1d5f1753e_1589193685453.jpeg"
        },
        {
          "name": "Nuke",
          "class_name": "de_nuke",
          "game_map_id": "de_nuke",
          "guid": "de_nuke",
          "image_lg": "https://assets.faceit-cdn.net/third_party/games/4f899245-2fa8-4e52-ad9a-4a363613c19e/assets/votables/2d11b059-8dc0-4b27-af45-383bb1f2edb3_1589578450447.jpeg",
          "image_sm": "https://assets.faceit-cdn.net/third_party/games/4f899245-2fa8-4e52-ad9a-4a363613c19e/assets/votables/ae5d92c0-2aee-45e3-9a53-396fa0b103f7_1589578446264.jpeg"
        },
        {
          "image_sm": "https://assets.faceit-cdn.net/third_party/games/4f899245-2fa8-4e52-ad9a-4a363613c19e/assets/votables/7654d0b5-bc0e-41bd-a59d-4ffa67da9a92_1589193763922.jpeg",
          "name": "Overpass",
          "class_name": "de_overpass",
          "game_map_id": "de_overpass",
          "guid": "de_overpass",
          "image_lg": "https://assets.faceit-cdn.net/third_party/games/4f899245-2fa8-4e52-ad9a-4a363613c19e/assets/votables/0fe0aa60-193e-4f0b-aa8a-64d3388291bf_1589195875398.jpeg"
        },
        {
          "class_name": "de_anubis",
          "game_map_id": "de_anubis",
          "guid": "de_anubis",
          "image_lg": "https://assets.faceit-cdn.net/third_party/games/4f899245-2fa8-4e52-ad9a-4a363613c19e/assets/votables/9fc5b28e-f228-4f7f-90af-992faba7c0d9_1589579908899.jpeg",
          "image_sm": "https://assets.faceit-cdn.net/third_party/games/4f899245-2fa8-4e52-ad9a-4a363613c19e/assets/votables/1421bd4f-91dc-4df8-8614-446b645e5a94_1589579904206.jpeg",
          "name": "Anubis"
        }
      ],
      "pick": [
        "de_inferno"
      ]
    }
  },
  "calculate_elo": false,
  "scheduled_at": 1693247400,
  "configured_at": 1693247593,
  "started_at": 1693248033,
  "finished_at": 1693251572,
  "demo_url": [
    "https://demos-europe-west2.faceit-cdn.net/csgo/1-a2ac26de-9f00-45d8-af78-30b7f3679c50-1-1.dem.gz"
  ],
  "chat_room_id": "match-1-a2ac26de-9f00-45d8-af78-30b7f3679c50",
  "best_of": 1,
  "results": {
    "winner": "faction1",
    "score": {
      "faction1": 1,
      "faction2": 0
    }
  },
  "detailed_results": [
    {
      "asc_score": false,
      "winner": "faction1",
      "factions": {
        "faction1": {
          "score": 1
        },
        "faction2": {
          "score": 0
        }
      }
    }
  ],
  "status": "FINISHED",
  "round": 5,
  "group": 1,
  "faceit_url": "https://www.faceit.com/{lang}/csgo/room/1-a2ac26de-9f00-45d8-af78-30b7f3679c50"
}